qaqc/__init__.py
qaqc/_testing.py
qaqc/constants.py
qaqc/errors.py
qaqc/typing.py
qaqc/core/__init__.py
qaqc/core/base.py
qaqc/core/flagsframe.py
qaqc/core/frame.py
qaqc/core/ops.py
qaqc/core/utils.py
qaqc/core/variable.py
qaqc-0.0.1.dist-info/METADATA
qaqc-0.0.1.dist-info/WHEEL
qaqc-0.0.1.dist-info/top_level.txt
qaqc-0.0.1.dist-info/RECORD
